README
setup.py
BlipApi.egg-info/PKG-INFO
BlipApi.egg-info/SOURCES.txt
BlipApi.egg-info/dependency_links.txt
BlipApi.egg-info/requires.txt
BlipApi.egg-info/top_level.txt
blipapi/__init__.py
blipapi/_utils.py
blipapi/avatar.py
blipapi/background.py
blipapi/blipapi.py
blipapi/bliposphere.py
blipapi/dashboard.py
blipapi/dirmsg.py
blipapi/movie.py
blipapi/notice.py
blipapi/picture.py
blipapi/privmsg.py
blipapi/recording.py
blipapi/shortlink.py
blipapi/status.py
blipapi/subscription.py
blipapi/tag.py
blipapi/tagsub.py
blipapi/token_req.py
blipapi/update.py
blipapi/user.py