Metadata-Version: 1.0
Name: BlipApi
Version: 0.02.11
Summary: Blip! (http://blip.pl) communication library.
Home-page: http://blipapi.googlecode.com
Author: Marcin Sztolcman
Author-email: marcin@urzenia.net
License: GPL
Keywords: blip microblogging library
Platform: UNKNOWN
Classifier: License :: OSI Approved :: GNU Library or Lesser General Public License (LGPL)
Classifier: Programming Language :: Python
Classifier: Development Status :: 5 - Production/Stable
Classifier: Intended Audience :: Developers
Classifier: Operating System :: OS Independent
Classifier: Topic :: Internet
Classifier: Topic :: Software Development :: Libraries :: Python Modules
